x_model/__init__.py
x_model/field.py
x_model/func.py
x_model/models.py
x_model/types.py
xn_model-1.0.24.dist-info/METADATA
xn_model-1.0.24.dist-info/WHEEL
xn_model-1.0.24.dist-info/top_level.txt
xn_model-1.0.24.dist-info/RECORD
