Metadata-Version: 2.4
Name: xn-model
Version: 1.0.24
Summary: Base model for xn-api
Author-email: Mike Artemiev <mixartemev@gmail.com>
License: MIT
Project-URL: Homepage, https://github.com/XyncNet/x-model
Project-URL: Repository, https://github.com/XyncNet/x-model
Keywords: tortoise,model,crud,generator,api,admin
Requires-Python: >=3.11
Requires-Dist: tortoise-orm[asyncpg]
Requires-Dist: pydantic
Provides-Extra: dev
Requires-Dist: pytest; extra == "dev"
Requires-Dist: python-dotenv; extra == "dev"
Requires-Dist: build; extra == "dev"
Requires-Dist: twine; extra == "dev"
